looplog/__init__.py
looplog/_version.py
looplog/demo.py
looplog/tests.py
looplog/utils.py
looplog-0.0.16.dist-info/METADATA
looplog-0.0.16.dist-info/WHEEL
looplog-0.0.16.dist-info/top_level.txt
looplog-0.0.16.dist-info/RECORD
