Metadata-Version: 2.4
Name: looplog
Version: 0.0.16
Summary: A little helper to log warnings/errors for processed
Author-email: Olivier Dalang <olivier.dalang@gmail.com>
License: MIT License
Project-URL: homepage, https://github.com/olivierdalang/looplog
Project-URL: repository, https://github.com/olivierdalang/looplog
Project-URL: tracker, https://github.com/olivierdalang/looplog/issues
Keywords: logging,warnings,errors
Classifier: Development Status :: 4 - Beta
Classifier: Intended Audience :: Developers
Classifier: License :: OSI Approved :: MIT License
Classifier: Programming Language :: Python :: 3
Requires-Python: >=3.0
Provides-Extra: dev
Requires-Dist: pre-commit; extra == "dev"
Requires-Dist: mypy; extra == "dev"
